py/__init__.py
py/practicals.py
mypyyy-0.0.1.dist-info/METADATA
mypyyy-0.0.1.dist-info/WHEEL
mypyyy-0.0.1.dist-info/top_level.txt
mypyyy-0.0.1.dist-info/RECORD
