Metadata-Version: 2.4
Name: mypyyy
Version: 0.0.1
Summary: A collection of Python practical codes with source introspection.
Project-URL: Homepage, https://github.com/yourusername/mypyyy
Classifier: Programming Language :: Python :: 3
Classifier: License :: OSI Approved :: MIT License
Classifier: Operating System :: OS Independent
Requires-Python: >=3.7
